reports/__init__.py
reports/payloads.py
reports/reports.py
ops_py_reports-0.6.0.dist-info/LICENSE
ops_py_reports-0.6.0.dist-info/METADATA
ops_py_reports-0.6.0.dist-info/WHEEL
ops_py_reports-0.6.0.dist-info/top_level.txt
ops_py_reports-0.6.0.dist-info/RECORD
