Metadata-Version: 2.1
Name: ops-py-reports
Version: 0.6.0
Summary: Post Key Vault Secrets report to webhook
License: MIT License
License-File: LICENSE
Requires-Dist: beautifulsoup4==4.12.3
Requires-Dist: pip==24.3.1
Requires-Dist: setuptools==75.5.0
Requires-Dist: soupsieve==2.6
Requires-Dist: wheel==0.45.0
